plone.app.debugtoolbar-1.4.0-py2.7-nspkg.pth
plone/app/debugtoolbar/__init__.py
plone/app/debugtoolbar/configure.zcml
plone/app/debugtoolbar/delayedwrite.py
plone/app/debugtoolbar/testing.py
plone/app/debugtoolbar/upgrades.py
plone/app/debugtoolbar/browser/__init__.py
plone/app/debugtoolbar/browser/catalog.pt
plone/app/debugtoolbar/browser/catalog.py
plone/app/debugtoolbar/browser/configure.zcml
plone/app/debugtoolbar/browser/context.pt
plone/app/debugtoolbar/browser/context.py
plone/app/debugtoolbar/browser/global.pt
plone/app/debugtoolbar/browser/global.py
plone/app/debugtoolbar/browser/interactive.pt
plone/app/debugtoolbar/browser/interactive.py
plone/app/debugtoolbar/browser/interfaces.py
plone/app/debugtoolbar/browser/published.pt
plone/app/debugtoolbar/browser/published.py
plone/app/debugtoolbar/browser/reload.pt
plone/app/debugtoolbar/browser/reload.py
plone/app/debugtoolbar/browser/request.pt
plone/app/debugtoolbar/browser/request.py
plone/app/debugtoolbar/browser/response.pt
plone/app/debugtoolbar/browser/response.py
plone/app/debugtoolbar/browser/theme.pt
plone/app/debugtoolbar/browser/theme.py
plone/app/debugtoolbar/browser/tile.py
plone/app/debugtoolbar/browser/toolbar.pt
plone/app/debugtoolbar/browser/toolbar.py
plone/app/debugtoolbar/browser/user.pt
plone/app/debugtoolbar/browser/user.py
plone/app/debugtoolbar/browser/versions.pt
plone/app/debugtoolbar/browser/versions.py
plone/app/debugtoolbar/browser/workflow.pt
plone/app/debugtoolbar/browser/workflow.py
plone/app/debugtoolbar/browser/resources/debugtoolbar.css
plone/app/debugtoolbar/browser/resources/debugtoolbar.js
plone/app/debugtoolbar/locales/plone.app.debugtoolbar.pot
plone/app/debugtoolbar/locales/plone.pot
plone/app/debugtoolbar/locales/es/LC_MESSAGES/plone.app.debugtoolbar.mo
plone/app/debugtoolbar/locales/es/LC_MESSAGES/plone.app.debugtoolbar.po
plone/app/debugtoolbar/locales/es/LC_MESSAGES/plone.mo
plone/app/debugtoolbar/locales/es/LC_MESSAGES/plone.po
plone.app.debugtoolbar-1.4.0.dist-info/METADATA
plone.app.debugtoolbar-1.4.0.dist-info/WHEEL
plone.app.debugtoolbar-1.4.0.dist-info/entry_points.txt
plone.app.debugtoolbar-1.4.0.dist-info/namespace_packages.txt
plone.app.debugtoolbar-1.4.0.dist-info/top_level.txt
plone.app.debugtoolbar-1.4.0.dist-info/RECORD
