Metadata-Version: 2.1
Name: plone.app.debugtoolbar
Version: 1.4.0
Summary: Debug toolbar for Plone
Home-page: https://pypi.org/project/plone.app.debugtoolbar/
Author: Martin Aspeli
Author-email: optilude@gmail.com
License: GPL
Keywords: plone debug toolbar
Platform: UNKNOWN
Classifier: Development Status :: 5 - Production/Stable
Classifier: Framework :: Plone
Classifier: Framework :: Plone :: 5.1
Classifier: Framework :: Plone :: 5.2
Classifier: Framework :: Plone :: 6.0
Classifier: License :: OSI Approved :: GNU General Public License (GPL)
Classifier: Programming Language :: Python
Classifier: Programming Language :: Python :: 2.7
Classifier: Programming Language :: Python :: 3.6
Classifier: Programming Language :: Python :: 3.7
Classifier: Programming Language :: Python :: 3.8
Classifier: Programming Language :: Python :: 3.9
Classifier: Programming Language :: Python :: 3.10
Classifier: Programming Language :: Python :: 3.11
Requires-Python: >=2.7,!=3.0.*,!=3.1.*,!=3.2.*,!=3.3.*,!=3.4.*,!=3.5.*
Requires-Dist: setuptools
Requires-Dist: Products.CMFPlone
Requires-Dist: zope.annotation
Requires-Dist: plone.transformchain
Requires-Dist: Paste
Requires-Dist: six
Provides-Extra: test
Requires-Dist: plone.app.testing ; extra == 'test'
